tests/__init__.py
tests/test_Webflow.py
webflowpy/Webflow.py
webflowpy/WebflowResponse.py
webflowpy/__init__.py
webflowpy/_version.py
webflowpy/log.py
webflowpy/settings.py
webflowpy/utils.py
Webflowpy-0.0.5.dist-info/LICENSE
Webflowpy-0.0.5.dist-info/METADATA
Webflowpy-0.0.5.dist-info/WHEEL
Webflowpy-0.0.5.dist-info/top_level.txt
Webflowpy-0.0.5.dist-info/RECORD
