Metadata-Version: 2.1
Name: Webflowpy
Version: 0.0.5
Summary: Python Webflow CMS API Client
Home-page: https://github.com/rfechtner/webflowpy
Author: Ron Fechtner
Author-email: ronfechtner@gmail.com
License: MIT License
Platform: UNKNOWN
License-File: LICENSE
Requires-Dist: psutil
Requires-Dist: colorama
Requires-Dist: requests
Requires-Dist: urllib3
Requires-Dist: typing
